dap_core/__init__.py
dap_core/actions.py
dap_core/common.py
dap_core/dap.py
dap_core/dependencies.py
dap_core/dependency_installers.py
dap_core/jar_dependency_installer.py
dap_core/meta_model.py
dap_core/no_action_error.py
dap_core/base_actions/__init__.py
dap_core/base_actions/clean_action_base.py
dap_core/base_actions/dap_action_base.py
dap_core/base_actions/default_action_base.py
dap_core/base_actions/deps_action_base.py
dap_core/base_actions/init_action_base.py
dap_core/util/__init__.py
dap_core/util/git_util.py
dap_core/util/str_util.py
dap_core/util/template_util.py
power_daps_core-0.0.6.dist-info/METADATA
power_daps_core-0.0.6.dist-info/WHEEL
power_daps_core-0.0.6.dist-info/entry_points.txt
power_daps_core-0.0.6.dist-info/top_level.txt
power_daps_core-0.0.6.dist-info/RECORD
